{
 "maker": "Eric.Lee",
 "date": "2021-02-01",
 "info": [
  {
   "bbox": [
    0.0,
    0.0,
    0.0,
    0.0
   ],
   "pts": {
    "0": {
     "x": 35,
     "y": 132
    },
    "1": {
     "x": 37,
     "y": 99
    },
    "2": {
     "x": 45,
     "y": 86
    },
    "3": {
     "x": 62,
     "y": 76
    },
    "4": {
     "x": 70,
     "y": 61
    },
    "5": {
     "x": 70,
     "y": 78
    },
    "6": {
     "x": 89,
     "y": 67
    },
    "7": {
     "x": 106,
     "y": 61
    },
    "8": {
     "x": 119,
     "y": 55
    },
    "9": {
     "x": 79,
     "y": 91
    },
    "10": {
     "x": 102,
     "y": 78
    },
    "11": {
     "x": 102,
     "y": 78
    },
    "12": {
     "x": 93,
     "y": 80
    },
    "13": {
     "x": 89,
     "y": 101
    },
    "14": {
     "x": 102,
     "y": 93
    },
    "15": {
     "x": 98,
     "y": 93
    },
    "16": {
     "x": 93,
     "y": 93
    },
    "17": {
     "x": 91,
     "y": 114
    },
    "18": {
     "x": 100,
     "y": 105
    },
    "19": {
     "x": 96,
     "y": 105
    },
    "20": {
     "x": 91,
     "y": 109
    }
   }
  }
 ]
}