{
 "maker": "Eric.Lee",
 "date": "2021-02-01",
 "info": [
  {
   "bbox": [
    0.0,
    0.0,
    0.0,
    0.0
   ],
   "pts": {
    "0": {
     "x": 140,
     "y": 304
    },
    "1": {
     "x": 168,
     "y": 293
    },
    "2": {
     "x": 195,
     "y": 210
    },
    "3": {
     "x": 212,
     "y": 177
    },
    "4": {
     "x": 228,
     "y": 116
    },
    "5": {
     "x": 190,
     "y": 215
    },
    "6": {
     "x": 201,
     "y": 188
    },
    "7": {
     "x": 217,
     "y": 160
    },
    "8": {
     "x": 223,
     "y": 127
    },
    "9": {
     "x": 151,
     "y": 188
    },
    "10": {
     "x": 168,
     "y": 232
    },
    "11": {
     "x": 162,
     "y": 276
    },
    "12": {
     "x": 157,
     "y": 271
    },
    "13": {
     "x": 118,
     "y": 193
    },
    "14": {
     "x": 123,
     "y": 232
    },
    "15": {
     "x": 129,
     "y": 271
    },
    "16": {
     "x": 129,
     "y": 271
    },
    "17": {
     "x": 79,
     "y": 210
    },
    "18": {
     "x": 85,
     "y": 243
    },
    "19": {
     "x": 101,
     "y": 271
    },
    "20": {
     "x": 101,
     "y": 271
    }
   }
  }
 ]
}