{
 "maker": "Eric.Lee",
 "date": "2021-02-01",
 "info": [
  {
   "bbox": [
    0.0,
    0.0,
    0.0,
    0.0
   ],
   "pts": {
    "0": {
     "x": 53,
     "y": 138
    },
    "1": {
     "x": 97,
     "y": 104
    },
    "2": {
     "x": 130,
     "y": 90
    },
    "3": {
     "x": 169,
     "y": 71
    },
    "4": {
     "x": 188,
     "y": 66
    },
    "5": {
     "x": 150,
     "y": 66
    },
    "6": {
     "x": 193,
     "y": 61
    },
    "7": {
     "x": 222,
     "y": 66
    },
    "8": {
     "x": 246,
     "y": 75
    },
    "9": {
     "x": 155,
     "y": 80
    },
    "10": {
     "x": 198,
     "y": 80
    },
    "11": {
     "x": 227,
     "y": 90
    },
    "12": {
     "x": 251,
     "y": 104
    },
    "13": {
     "x": 150,
     "y": 109
    },
    "14": {
     "x": 193,
     "y": 109
    },
    "15": {
     "x": 222,
     "y": 119
    },
    "16": {
     "x": 241,
     "y": 133
    },
    "17": {
     "x": 145,
     "y": 138
    },
    "18": {
     "x": 183,
     "y": 143
    },
    "19": {
     "x": 207,
     "y": 152
    },
    "20": {
     "x": 227,
     "y": 162
    }
   }
  }
 ]
}