{
 "maker": "Eric.Lee",
 "date": "2021-02-01",
 "info": [
  {
   "bbox": [
    0.0,
    0.0,
    0.0,
    0.0
   ],
   "pts": {
    "0": {
     "x": 133,
     "y": 213
    },
    "1": {
     "x": 188,
     "y": 219
    },
    "2": {
     "x": 226,
     "y": 208
    },
    "3": {
     "x": 270,
     "y": 197
    },
    "4": {
     "x": 309,
     "y": 175
    },
    "5": {
     "x": 210,
     "y": 197
    },
    "6": {
     "x": 243,
     "y": 164
    },
    "7": {
     "x": 270,
     "y": 136
    },
    "8": {
     "x": 314,
     "y": 175
    },
    "9": {
     "x": 177,
     "y": 191
    },
    "10": {
     "x": 199,
     "y": 153
    },
    "11": {
     "x": 221,
     "y": 125
    },
    "12": {
     "x": 248,
     "y": 87
    },
    "13": {
     "x": 133,
     "y": 191
    },
    "14": {
     "x": 138,
     "y": 158
    },
    "15": {
     "x": 144,
     "y": 147
    },
    "16": {
     "x": 155,
     "y": 114
    },
    "17": {
     "x": 94,
     "y": 191
    },
    "18": {
     "x": 83,
     "y": 169
    },
    "19": {
     "x": 67,
     "y": 153
    },
    "20": {
     "x": 50,
     "y": 125
    }
   }
  }
 ]
}