{
 "maker": "Eric.Lee",
 "date": "2021-02-01",
 "info": [
  {
   "bbox": [
    0.0,
    0.0,
    0.0,
    0.0
   ],
   "pts": {
    "0": {
     "x": 101,
     "y": 60
    },
    "1": {
     "x": 90,
     "y": 95
    },
    "2": {
     "x": 73,
     "y": 114
    },
    "3": {
     "x": 60,
     "y": 123
    },
    "4": {
     "x": 55,
     "y": 123
    },
    "5": {
     "x": 47,
     "y": 106
    },
    "6": {
     "x": 29,
     "y": 123
    },
    "7": {
     "x": 27,
     "y": 125
    },
    "8": {
     "x": 32,
     "y": 121
    },
    "9": {
     "x": 40,
     "y": 91
    },
    "10": {
     "x": 23,
     "y": 104
    },
    "11": {
     "x": 21,
     "y": 112
    },
    "12": {
     "x": 25,
     "y": 114
    },
    "13": {
     "x": 38,
     "y": 76
    },
    "14": {
     "x": 23,
     "y": 84
    },
    "15": {
     "x": 19,
     "y": 93
    },
    "16": {
     "x": 19,
     "y": 99
    },
    "17": {
     "x": 38,
     "y": 60
    },
    "18": {
     "x": 25,
     "y": 67
    },
    "19": {
     "x": 17,
     "y": 73
    },
    "20": {
     "x": 12,
     "y": 80
    }
   }
  }
 ]
}