{
 "maker": "Eric.Lee",
 "date": "2021-02-01",
 "info": [
  {
   "bbox": [
    0.0,
    0.0,
    0.0,
    0.0
   ],
   "pts": {
    "0": {
     "x": 62,
     "y": 37
    },
    "1": {
     "x": 49,
     "y": 46
    },
    "2": {
     "x": 34,
     "y": 61
    },
    "3": {
     "x": 30,
     "y": 74
    },
    "4": {
     "x": 27,
     "y": 85
    },
    "5": {
     "x": 27,
     "y": 70
    },
    "6": {
     "x": 17,
     "y": 91
    },
    "7": {
     "x": 19,
     "y": 100
    },
    "8": {
     "x": 21,
     "y": 100
    },
    "9": {
     "x": 36,
     "y": 72
    },
    "10": {
     "x": 27,
     "y": 94
    },
    "11": {
     "x": 32,
     "y": 111
    },
    "12": {
     "x": 36,
     "y": 122
    },
    "13": {
     "x": 45,
     "y": 74
    },
    "14": {
     "x": 38,
     "y": 96
    },
    "15": {
     "x": 40,
     "y": 109
    },
    "16": {
     "x": 47,
     "y": 122
    },
    "17": {
     "x": 53,
     "y": 76
    },
    "18": {
     "x": 49,
     "y": 94
    },
    "19": {
     "x": 51,
     "y": 100
    },
    "20": {
     "x": 58,
     "y": 87
    }
   }
  }
 ]
}