{
 "maker": "Eric.Lee",
 "date": "2021-02-01",
 "info": [
  {
   "bbox": [
    0.0,
    0.0,
    0.0,
    0.0
   ],
   "pts": {
    "0": {
     "x": 56,
     "y": 149
    },
    "1": {
     "x": 42,
     "y": 114
    },
    "2": {
     "x": 47,
     "y": 94
    },
    "3": {
     "x": 65,
     "y": 78
    },
    "4": {
     "x": 76,
     "y": 67
    },
    "5": {
     "x": 82,
     "y": 76
    },
    "6": {
     "x": 93,
     "y": 58
    },
    "7": {
     "x": 96,
     "y": 58
    },
    "8": {
     "x": 89,
     "y": 67
    },
    "9": {
     "x": 100,
     "y": 92
    },
    "10": {
     "x": 113,
     "y": 74
    },
    "11": {
     "x": 107,
     "y": 74
    },
    "12": {
     "x": 100,
     "y": 78
    },
    "13": {
     "x": 109,
     "y": 105
    },
    "14": {
     "x": 120,
     "y": 87
    },
    "15": {
     "x": 111,
     "y": 90
    },
    "16": {
     "x": 104,
     "y": 94
    },
    "17": {
     "x": 116,
     "y": 118
    },
    "18": {
     "x": 124,
     "y": 107
    },
    "19": {
     "x": 118,
     "y": 103
    },
    "20": {
     "x": 111,
     "y": 110
    }
   }
  }
 ]
}