{
 "maker": "Eric.Lee",
 "date": "2021-02-01",
 "info": [
  {
   "bbox": [
    0.0,
    0.0,
    0.0,
    0.0
   ],
   "pts": {
    "0": {
     "x": 47,
     "y": 52
    },
    "1": {
     "x": 40,
     "y": 49
    },
    "2": {
     "x": 29,
     "y": 48
    },
    "3": {
     "x": 21,
     "y": 50
    },
    "4": {
     "x": 14,
     "y": 55
    },
    "5": {
     "x": 31,
     "y": 26
    },
    "6": {
     "x": 24,
     "y": 22
    },
    "7": {
     "x": 17,
     "y": 24
    },
    "8": {
     "x": 14,
     "y": 31
    },
    "9": {
     "x": 32,
     "y": 24
    },
    "10": {
     "x": 24,
     "y": 20
    },
    "11": {
     "x": 17,
     "y": 25
    },
    "12": {
     "x": 14,
     "y": 31
    },
    "13": {
     "x": 32,
     "y": 23
    },
    "14": {
     "x": 23,
     "y": 18
    },
    "15": {
     "x": 17,
     "y": 24
    },
    "16": {
     "x": 15,
     "y": 31
    },
    "17": {
     "x": 31,
     "y": 23
    },
    "18": {
     "x": 24,
     "y": 21
    },
    "19": {
     "x": 18,
     "y": 24
    },
    "20": {
     "x": 16,
     "y": 31
    }
   }
  }
 ]
}