{
 "maker": "Eric.Lee",
 "date": "2021-02-01",
 "info": [
  {
   "bbox": [
    0.0,
    0.0,
    0.0,
    0.0
   ],
   "pts": {
    "0": {
     "x": 62,
     "y": 112
    },
    "1": {
     "x": 44,
     "y": 95
    },
    "2": {
     "x": 36,
     "y": 78
    },
    "3": {
     "x": 24,
     "y": 69
    },
    "4": {
     "x": 12,
     "y": 64
    },
    "5": {
     "x": 56,
     "y": 50
    },
    "6": {
     "x": 36,
     "y": 47
    },
    "7": {
     "x": 24,
     "y": 55
    },
    "8": {
     "x": 15,
     "y": 67
    },
    "9": {
     "x": 63,
     "y": 53
    },
    "10": {
     "x": 37,
     "y": 59
    },
    "11": {
     "x": 29,
     "y": 74
    },
    "12": {
     "x": 29,
     "y": 83
    },
    "13": {
     "x": 68,
     "y": 64
    },
    "14": {
     "x": 46,
     "y": 64
    },
    "15": {
     "x": 36,
     "y": 79
    },
    "16": {
     "x": 32,
     "y": 88
    },
    "17": {
     "x": 74,
     "y": 74
    },
    "18": {
     "x": 60,
     "y": 72
    },
    "19": {
     "x": 48,
     "y": 76
    },
    "20": {
     "x": 36,
     "y": 81
    }
   }
  }
 ]
}