{
 "maker": "Eric.Lee",
 "date": "2021-02-01",
 "info": [
  {
   "bbox": [
    0.0,
    0.0,
    0.0,
    0.0
   ],
   "pts": {
    "0": {
     "x": 197,
     "y": 303
    },
    "1": {
     "x": 250,
     "y": 269
    },
    "2": {
     "x": 284,
     "y": 243
    },
    "3": {
     "x": 317,
     "y": 216
    },
    "4": {
     "x": 351,
     "y": 189
    },
    "5": {
     "x": 250,
     "y": 209
    },
    "6": {
     "x": 277,
     "y": 182
    },
    "7": {
     "x": 290,
     "y": 162
    },
    "8": {
     "x": 304,
     "y": 129
    },
    "9": {
     "x": 217,
     "y": 203
    },
    "10": {
     "x": 217,
     "y": 149
    },
    "11": {
     "x": 217,
     "y": 116
    },
    "12": {
     "x": 224,
     "y": 69
    },
    "13": {
     "x": 183,
     "y": 216
    },
    "14": {
     "x": 170,
     "y": 176
    },
    "15": {
     "x": 150,
     "y": 156
    },
    "16": {
     "x": 143,
     "y": 142
    },
    "17": {
     "x": 157,
     "y": 236
    },
    "18": {
     "x": 123,
     "y": 216
    },
    "19": {
     "x": 97,
     "y": 216
    },
    "20": {
     "x": 76,
     "y": 216
    }
   }
  }
 ]
}