{
 "maker": "Eric.Lee",
 "date": "2021-02-01",
 "info": [
  {
   "bbox": [
    0.0,
    0.0,
    0.0,
    0.0
   ],
   "pts": {
    "0": {
     "x": 124,
     "y": 94
    },
    "1": {
     "x": 109,
     "y": 80
    },
    "2": {
     "x": 101,
     "y": 66
    },
    "3": {
     "x": 90,
     "y": 57
    },
    "4": {
     "x": 84,
     "y": 49
    },
    "5": {
     "x": 81,
     "y": 69
    },
    "6": {
     "x": 70,
     "y": 57
    },
    "7": {
     "x": 55,
     "y": 57
    },
    "8": {
     "x": 36,
     "y": 57
    },
    "9": {
     "x": 81,
     "y": 83
    },
    "10": {
     "x": 64,
     "y": 80
    },
    "11": {
     "x": 38,
     "y": 86
    },
    "12": {
     "x": 21,
     "y": 91
    },
    "13": {
     "x": 78,
     "y": 97
    },
    "14": {
     "x": 64,
     "y": 97
    },
    "15": {
     "x": 41,
     "y": 100
    },
    "16": {
     "x": 24,
     "y": 100
    },
    "17": {
     "x": 81,
     "y": 114
    },
    "18": {
     "x": 70,
     "y": 120
    },
    "19": {
     "x": 58,
     "y": 125
    },
    "20": {
     "x": 44,
     "y": 128
    }
   }
  }
 ]
}