{
 "maker": "Eric.Lee",
 "date": "2021-02-01",
 "info": [
  {
   "bbox": [
    0.0,
    0.0,
    0.0,
    0.0
   ],
   "pts": {
    "0": {
     "x": 25,
     "y": 107
    },
    "1": {
     "x": 19,
     "y": 86
    },
    "2": {
     "x": 18,
     "y": 71
    },
    "3": {
     "x": 16,
     "y": 56
    },
    "4": {
     "x": 18,
     "y": 41
    },
    "5": {
     "x": 28,
     "y": 66
    },
    "6": {
     "x": 40,
     "y": 56
    },
    "7": {
     "x": 55,
     "y": 50
    },
    "8": {
     "x": 66,
     "y": 45
    },
    "9": {
     "x": 36,
     "y": 74
    },
    "10": {
     "x": 52,
     "y": 63
    },
    "11": {
     "x": 67,
     "y": 56
    },
    "12": {
     "x": 79,
     "y": 53
    },
    "13": {
     "x": 42,
     "y": 81
    },
    "14": {
     "x": 58,
     "y": 72
    },
    "15": {
     "x": 72,
     "y": 65
    },
    "16": {
     "x": 82,
     "y": 60
    },
    "17": {
     "x": 48,
     "y": 89
    },
    "18": {
     "x": 60,
     "y": 81
    },
    "19": {
     "x": 69,
     "y": 75
    },
    "20": {
     "x": 76,
     "y": 69
    }
   }
  }
 ]
}