{
 "maker": "Eric.Lee",
 "date": "2021-02-01",
 "info": [
  {
   "bbox": [
    0.0,
    0.0,
    0.0,
    0.0
   ],
   "pts": {
    "0": {
     "x": 91,
     "y": 95
    },
    "1": {
     "x": 76,
     "y": 68
    },
    "2": {
     "x": 64,
     "y": 49
    },
    "3": {
     "x": 55,
     "y": 32
    },
    "4": {
     "x": 45,
     "y": 39
    },
    "5": {
     "x": 64,
     "y": 81
    },
    "6": {
     "x": 34,
     "y": 89
    },
    "7": {
     "x": 24,
     "y": 89
    },
    "8": {
     "x": 30,
     "y": 87
    },
    "9": {
     "x": 66,
     "y": 97
    },
    "10": {
     "x": 30,
     "y": 106
    },
    "11": {
     "x": 24,
     "y": 99
    },
    "12": {
     "x": 30,
     "y": 95
    },
    "13": {
     "x": 64,
     "y": 114
    },
    "14": {
     "x": 32,
     "y": 118
    },
    "15": {
     "x": 28,
     "y": 114
    },
    "16": {
     "x": 32,
     "y": 108
    },
    "17": {
     "x": 66,
     "y": 129
    },
    "18": {
     "x": 41,
     "y": 131
    },
    "19": {
     "x": 32,
     "y": 127
    },
    "20": {
     "x": 34,
     "y": 120
    }
   }
  }
 ]
}