{
 "maker": "Eric.Lee",
 "date": "2021-02-01",
 "info": [
  {
   "bbox": [
    0.0,
    0.0,
    0.0,
    0.0
   ],
   "pts": {
    "0": {
     "x": 100,
     "y": 71
    },
    "1": {
     "x": 83,
     "y": 65
    },
    "2": {
     "x": 71,
     "y": 65
    },
    "3": {
     "x": 56,
     "y": 71
    },
    "4": {
     "x": 48,
     "y": 75
    },
    "5": {
     "x": 60,
     "y": 69
    },
    "6": {
     "x": 44,
     "y": 77
    },
    "7": {
     "x": 32,
     "y": 85
    },
    "8": {
     "x": 23,
     "y": 92
    },
    "9": {
     "x": 65,
     "y": 81
    },
    "10": {
     "x": 46,
     "y": 90
    },
    "11": {
     "x": 34,
     "y": 98
    },
    "12": {
     "x": 25,
     "y": 106
    },
    "13": {
     "x": 71,
     "y": 90
    },
    "14": {
     "x": 54,
     "y": 98
    },
    "15": {
     "x": 42,
     "y": 106
    },
    "16": {
     "x": 32,
     "y": 110
    },
    "17": {
     "x": 77,
     "y": 98
    },
    "18": {
     "x": 69,
     "y": 102
    },
    "19": {
     "x": 60,
     "y": 106
    },
    "20": {
     "x": 50,
     "y": 110
    }
   }
  }
 ]
}