{
 "maker": "Eric.Lee",
 "date": "2021-02-01",
 "info": [
  {
   "bbox": [
    0.0,
    0.0,
    0.0,
    0.0
   ],
   "pts": {
    "0": {
     "x": 130,
     "y": 229
    },
    "1": {
     "x": 164,
     "y": 225
    },
    "2": {
     "x": 185,
     "y": 212
    },
    "3": {
     "x": 211,
     "y": 212
    },
    "4": {
     "x": 206,
     "y": 238
    },
    "5": {
     "x": 181,
     "y": 161
    },
    "6": {
     "x": 185,
     "y": 131
    },
    "7": {
     "x": 194,
     "y": 114
    },
    "8": {
     "x": 219,
     "y": 106
    },
    "9": {
     "x": 151,
     "y": 165
    },
    "10": {
     "x": 151,
     "y": 136
    },
    "11": {
     "x": 155,
     "y": 110
    },
    "12": {
     "x": 160,
     "y": 72
    },
    "13": {
     "x": 117,
     "y": 174
    },
    "14": {
     "x": 113,
     "y": 140
    },
    "15": {
     "x": 109,
     "y": 119
    },
    "16": {
     "x": 109,
     "y": 85
    },
    "17": {
     "x": 83,
     "y": 187
    },
    "18": {
     "x": 66,
     "y": 165
    },
    "19": {
     "x": 49,
     "y": 148
    },
    "20": {
     "x": 36,
     "y": 127
    }
   }
  }
 ]
}