{
 "maker": "Eric.Lee",
 "date": "2021-02-01",
 "info": [
  {
   "bbox": [
    0.0,
    0.0,
    0.0,
    0.0
   ],
   "pts": {
    "0": {
     "x": 99,
     "y": 142
    },
    "1": {
     "x": 126,
     "y": 145
    },
    "2": {
     "x": 144,
     "y": 142
    },
    "3": {
     "x": 159,
     "y": 139
    },
    "4": {
     "x": 181,
     "y": 124
    },
    "5": {
     "x": 135,
     "y": 112
    },
    "6": {
     "x": 144,
     "y": 103
    },
    "7": {
     "x": 150,
     "y": 93
    },
    "8": {
     "x": 165,
     "y": 84
    },
    "9": {
     "x": 108,
     "y": 112
    },
    "10": {
     "x": 111,
     "y": 97
    },
    "11": {
     "x": 111,
     "y": 87
    },
    "12": {
     "x": 108,
     "y": 60
    },
    "13": {
     "x": 80,
     "y": 115
    },
    "14": {
     "x": 77,
     "y": 100
    },
    "15": {
     "x": 74,
     "y": 87
    },
    "16": {
     "x": 71,
     "y": 57
    },
    "17": {
     "x": 53,
     "y": 127
    },
    "18": {
     "x": 44,
     "y": 118
    },
    "19": {
     "x": 38,
     "y": 115
    },
    "20": {
     "x": 29,
     "y": 106
    }
   }
  }
 ]
}