{"maker": "Eric.Lee", "modifier": "wangyu", "date": "2021-02-01", "modified_time": "2022-03-29", "info": [{"bbox": [0.0, 0.0, 0.0, 0.0], "pts": {"0": {"x": 39, "y": 82}, "1": {"x": 40, "y": 72}, "2": {"x": 39, "y": 60}, "3": {"x": 37, "y": 51}, "4": {"x": 31, "y": 43}, "5": {"x": 45, "y": 54}, "6": {"x": 43, "y": 40}, "7": {"x": 37, "y": 33}, "8": {"x": 31, "y": 27}, "9": {"x": 40, "y": 55}, "10": {"x": 31, "y": 43}, "11": {"x": 22, "y": 36}, "12": {"x": 13, "y": 33}, "13": {"x": 34, "y": 57}, "14": {"x": 25, "y": 48}, "15": {"x": 16, "y": 45}, "16": {"x": 10, "y": 45}, "17": {"x": 28, "y": 61}, "18": {"x": 22, "y": 52}, "19": {"x": 15, "y": 49}, "20": {"x": 9, "y": 48}}, "fingers": [0.0, 0.0, 0.0, 0.0, 0.0]}]}