{
 "maker": "Eric.Lee",
 "date": "2021-02-01",
 "info": [
  {
   "bbox": [
    0.0,
    0.0,
    0.0,
    0.0
   ],
   "pts": {
    "0": {
     "x": 215,
     "y": 75
    },
    "1": {
     "x": 206,
     "y": 118
    },
    "2": {
     "x": 176,
     "y": 144
    },
    "3": {
     "x": 154,
     "y": 162
    },
    "4": {
     "x": 141,
     "y": 179
    },
    "5": {
     "x": 124,
     "y": 106
    },
    "6": {
     "x": 90,
     "y": 101
    },
    "7": {
     "x": 60,
     "y": 93
    },
    "8": {
     "x": 38,
     "y": 84
    },
    "9": {
     "x": 116,
     "y": 84
    },
    "10": {
     "x": 77,
     "y": 75
    },
    "11": {
     "x": 47,
     "y": 67
    },
    "12": {
     "x": 21,
     "y": 54
    },
    "13": {
     "x": 120,
     "y": 75
    },
    "14": {
     "x": 85,
     "y": 62
    },
    "15": {
     "x": 55,
     "y": 54
    },
    "16": {
     "x": 38,
     "y": 41
    },
    "17": {
     "x": 124,
     "y": 67
    },
    "18": {
     "x": 107,
     "y": 62
    },
    "19": {
     "x": 90,
     "y": 54
    },
    "20": {
     "x": 72,
     "y": 45
    }
   }
  }
 ]
}