{
 "maker": "Eric.Lee",
 "date": "2021-02-01",
 "info": [
  {
   "bbox": [
    0.0,
    0.0,
    0.0,
    0.0
   ],
   "pts": {
    "0": {
     "x": 70,
     "y": 49
    },
    "1": {
     "x": 106,
     "y": 63
    },
    "2": {
     "x": 115,
     "y": 90
    },
    "3": {
     "x": 120,
     "y": 108
    },
    "4": {
     "x": 115,
     "y": 127
    },
    "5": {
     "x": 124,
     "y": 113
    },
    "6": {
     "x": 142,
     "y": 140
    },
    "7": {
     "x": 156,
     "y": 167
    },
    "8": {
     "x": 165,
     "y": 185
    },
    "9": {
     "x": 106,
     "y": 127
    },
    "10": {
     "x": 111,
     "y": 158
    },
    "11": {
     "x": 115,
     "y": 185
    },
    "12": {
     "x": 120,
     "y": 213
    },
    "13": {
     "x": 83,
     "y": 131
    },
    "14": {
     "x": 88,
     "y": 158
    },
    "15": {
     "x": 88,
     "y": 185
    },
    "16": {
     "x": 93,
     "y": 208
    },
    "17": {
     "x": 61,
     "y": 131
    },
    "18": {
     "x": 52,
     "y": 145
    },
    "19": {
     "x": 47,
     "y": 163
    },
    "20": {
     "x": 38,
     "y": 176
    }
   }
  }
 ]
}