{
 "maker": "Eric.Lee",
 "date": "2021-02-01",
 "info": [
  {
   "bbox": [
    0.0,
    0.0,
    0.0,
    0.0
   ],
   "pts": {
    "0": {
     "x": 70,
     "y": 216
    },
    "1": {
     "x": 104,
     "y": 177
    },
    "2": {
     "x": 131,
     "y": 144
    },
    "3": {
     "x": 154,
     "y": 121
    },
    "4": {
     "x": 142,
     "y": 94
    },
    "5": {
     "x": 193,
     "y": 160
    },
    "6": {
     "x": 231,
     "y": 155
    },
    "7": {
     "x": 265,
     "y": 144
    },
    "8": {
     "x": 287,
     "y": 138
    },
    "9": {
     "x": 204,
     "y": 183
    },
    "10": {
     "x": 243,
     "y": 183
    },
    "11": {
     "x": 282,
     "y": 183
    },
    "12": {
     "x": 309,
     "y": 183
    },
    "13": {
     "x": 198,
     "y": 210
    },
    "14": {
     "x": 237,
     "y": 216
    },
    "15": {
     "x": 265,
     "y": 221
    },
    "16": {
     "x": 293,
     "y": 221
    },
    "17": {
     "x": 193,
     "y": 233
    },
    "18": {
     "x": 226,
     "y": 238
    },
    "19": {
     "x": 259,
     "y": 238
    },
    "20": {
     "x": 287,
     "y": 238
    }
   }
  }
 ]
}