{
 "maker": "Eric.Lee",
 "date": "2021-02-01",
 "info": [
  {
   "bbox": [
    0.0,
    0.0,
    0.0,
    0.0
   ],
   "pts": {
    "0": {
     "x": 84,
     "y": 188
    },
    "1": {
     "x": 100,
     "y": 145
    },
    "2": {
     "x": 122,
     "y": 117
    },
    "3": {
     "x": 138,
     "y": 95
    },
    "4": {
     "x": 133,
     "y": 68
    },
    "5": {
     "x": 182,
     "y": 128
    },
    "6": {
     "x": 215,
     "y": 117
    },
    "7": {
     "x": 242,
     "y": 117
    },
    "8": {
     "x": 264,
     "y": 112
    },
    "9": {
     "x": 193,
     "y": 150
    },
    "10": {
     "x": 237,
     "y": 145
    },
    "11": {
     "x": 269,
     "y": 139
    },
    "12": {
     "x": 297,
     "y": 134
    },
    "13": {
     "x": 193,
     "y": 183
    },
    "14": {
     "x": 237,
     "y": 177
    },
    "15": {
     "x": 264,
     "y": 172
    },
    "16": {
     "x": 297,
     "y": 161
    },
    "17": {
     "x": 187,
     "y": 210
    },
    "18": {
     "x": 215,
     "y": 216
    },
    "19": {
     "x": 237,
     "y": 221
    },
    "20": {
     "x": 253,
     "y": 227
    }
   }
  }
 ]
}