{
 "maker": "Eric.Lee",
 "date": "2021-02-01",
 "info": [
  {
   "bbox": [
    0.0,
    0.0,
    0.0,
    0.0
   ],
   "pts": {
    "0": {
     "x": 69,
     "y": 53
    },
    "1": {
     "x": 38,
     "y": 49
    },
    "2": {
     "x": 26,
     "y": 55
    },
    "3": {
     "x": 21,
     "y": 64
    },
    "4": {
     "x": 17,
     "y": 74
    },
    "5": {
     "x": 53,
     "y": 59
    },
    "6": {
     "x": 48,
     "y": 74
    },
    "7": {
     "x": 41,
     "y": 88
    },
    "8": {
     "x": 33,
     "y": 100
    },
    "9": {
     "x": 66,
     "y": 65
    },
    "10": {
     "x": 68,
     "y": 79
    },
    "11": {
     "x": 51,
     "y": 94
    },
    "12": {
     "x": 39,
     "y": 103
    },
    "13": {
     "x": 78,
     "y": 71
    },
    "14": {
     "x": 81,
     "y": 86
    },
    "15": {
     "x": 63,
     "y": 101
    },
    "16": {
     "x": 48,
     "y": 109
    },
    "17": {
     "x": 86,
     "y": 82
    },
    "18": {
     "x": 90,
     "y": 94
    },
    "19": {
     "x": 86,
     "y": 103
    },
    "20": {
     "x": 75,
     "y": 110
    }
   }
  }
 ]
}