{
 "maker": "Eric.Lee",
 "date": "2021-02-01",
 "info": [
  {
   "bbox": [
    0.0,
    0.0,
    0.0,
    0.0
   ],
   "pts": {
    "0": {
     "x": 178,
     "y": 170
    },
    "1": {
     "x": 164,
     "y": 128
    },
    "2": {
     "x": 136,
     "y": 100
    },
    "3": {
     "x": 115,
     "y": 83
    },
    "4": {
     "x": 94,
     "y": 62
    },
    "5": {
     "x": 101,
     "y": 97
    },
    "6": {
     "x": 80,
     "y": 86
    },
    "7": {
     "x": 66,
     "y": 79
    },
    "8": {
     "x": 59,
     "y": 79
    },
    "9": {
     "x": 87,
     "y": 114
    },
    "10": {
     "x": 66,
     "y": 104
    },
    "11": {
     "x": 55,
     "y": 93
    },
    "12": {
     "x": 45,
     "y": 83
    },
    "13": {
     "x": 83,
     "y": 135
    },
    "14": {
     "x": 69,
     "y": 128
    },
    "15": {
     "x": 55,
     "y": 121
    },
    "16": {
     "x": 45,
     "y": 111
    },
    "17": {
     "x": 83,
     "y": 160
    },
    "18": {
     "x": 73,
     "y": 156
    },
    "19": {
     "x": 66,
     "y": 153
    },
    "20": {
     "x": 66,
     "y": 153
    }
   }
  }
 ]
}