{
 "maker": "Eric.Lee",
 "date": "2021-02-01",
 "info": [
  {
   "bbox": [
    0.0,
    0.0,
    0.0,
    0.0
   ],
   "pts": {
    "0": {
     "x": 43,
     "y": 43
    },
    "1": {
     "x": 64,
     "y": 45
    },
    "2": {
     "x": 88,
     "y": 54
    },
    "3": {
     "x": 104,
     "y": 60
    },
    "4": {
     "x": 121,
     "y": 67
    },
    "5": {
     "x": 80,
     "y": 54
    },
    "6": {
     "x": 93,
     "y": 65
    },
    "7": {
     "x": 104,
     "y": 76
    },
    "8": {
     "x": 113,
     "y": 87
    },
    "9": {
     "x": 64,
     "y": 54
    },
    "10": {
     "x": 78,
     "y": 67
    },
    "11": {
     "x": 84,
     "y": 78
    },
    "12": {
     "x": 95,
     "y": 91
    },
    "13": {
     "x": 56,
     "y": 58
    },
    "14": {
     "x": 69,
     "y": 67
    },
    "15": {
     "x": 73,
     "y": 80
    },
    "16": {
     "x": 82,
     "y": 89
    },
    "17": {
     "x": 49,
     "y": 63
    },
    "18": {
     "x": 60,
     "y": 69
    },
    "19": {
     "x": 67,
     "y": 78
    },
    "20": {
     "x": 69,
     "y": 82
    }
   }
  }
 ]
}