{
 "maker": "Eric.Lee",
 "date": "2021-02-01",
 "info": [
  {
   "bbox": [
    0.0,
    0.0,
    0.0,
    0.0
   ],
   "pts": {
    "0": {
     "x": 265,
     "y": 90
    },
    "1": {
     "x": 249,
     "y": 150
    },
    "2": {
     "x": 217,
     "y": 191
    },
    "3": {
     "x": 189,
     "y": 215
    },
    "4": {
     "x": 160,
     "y": 247
    },
    "5": {
     "x": 144,
     "y": 163
    },
    "6": {
     "x": 120,
     "y": 199
    },
    "7": {
     "x": 108,
     "y": 219
    },
    "8": {
     "x": 96,
     "y": 235
    },
    "9": {
     "x": 132,
     "y": 142
    },
    "10": {
     "x": 104,
     "y": 171
    },
    "11": {
     "x": 96,
     "y": 195
    },
    "12": {
     "x": 88,
     "y": 207
    },
    "13": {
     "x": 136,
     "y": 126
    },
    "14": {
     "x": 112,
     "y": 146
    },
    "15": {
     "x": 100,
     "y": 171
    },
    "16": {
     "x": 100,
     "y": 183
    },
    "17": {
     "x": 144,
     "y": 114
    },
    "18": {
     "x": 132,
     "y": 126
    },
    "19": {
     "x": 120,
     "y": 138
    },
    "20": {
     "x": 112,
     "y": 150
    }
   }
  }
 ]
}