{
 "maker": "Eric.Lee",
 "date": "2021-02-01",
 "info": [
  {
   "bbox": [
    0.0,
    0.0,
    0.0,
    0.0
   ],
   "pts": {
    "0": {
     "x": 16,
     "y": 46
    },
    "1": {
     "x": 26,
     "y": 31
    },
    "2": {
     "x": 33,
     "y": 26
    },
    "3": {
     "x": 39,
     "y": 23
    },
    "4": {
     "x": 46,
     "y": 22
    },
    "5": {
     "x": 53,
     "y": 39
    },
    "6": {
     "x": 60,
     "y": 39
    },
    "7": {
     "x": 61,
     "y": 40
    },
    "8": {
     "x": 61,
     "y": 41
    },
    "9": {
     "x": 53,
     "y": 48
    },
    "10": {
     "x": 61,
     "y": 48
    },
    "11": {
     "x": 62,
     "y": 49
    },
    "12": {
     "x": 58,
     "y": 49
    },
    "13": {
     "x": 51,
     "y": 56
    },
    "14": {
     "x": 57,
     "y": 58
    },
    "15": {
     "x": 57,
     "y": 58
    },
    "16": {
     "x": 56,
     "y": 57
    },
    "17": {
     "x": 47,
     "y": 64
    },
    "18": {
     "x": 54,
     "y": 67
    },
    "19": {
     "x": 52,
     "y": 66
    },
    "20": {
     "x": 49,
     "y": 66
    }
   }
  }
 ]
}