{
 "maker": "Eric.Lee",
 "date": "2021-02-01",
 "info": [
  {
   "bbox": [
    0.0,
    0.0,
    0.0,
    0.0
   ],
   "pts": {
    "0": {
     "x": 18,
     "y": 18
    },
    "1": {
     "x": 28,
     "y": 30
    },
    "2": {
     "x": 31,
     "y": 43
    },
    "3": {
     "x": 31,
     "y": 48
    },
    "4": {
     "x": 31,
     "y": 52
    },
    "5": {
     "x": 25,
     "y": 52
    },
    "6": {
     "x": 25,
     "y": 59
    },
    "7": {
     "x": 26,
     "y": 67
    },
    "8": {
     "x": 28,
     "y": 75
    },
    "9": {
     "x": 17,
     "y": 52
    },
    "10": {
     "x": 18,
     "y": 62
    },
    "11": {
     "x": 20,
     "y": 70
    },
    "12": {
     "x": 22,
     "y": 78
    },
    "13": {
     "x": 12,
     "y": 52
    },
    "14": {
     "x": 12,
     "y": 61
    },
    "15": {
     "x": 12,
     "y": 69
    },
    "16": {
     "x": 13,
     "y": 77
    },
    "17": {
     "x": 7,
     "y": 51
    },
    "18": {
     "x": 7,
     "y": 57
    },
    "19": {
     "x": 9,
     "y": 64
    },
    "20": {
     "x": 10,
     "y": 67
    }
   }
  }
 ]
}