{
 "maker": "Eric.Lee",
 "date": "2021-02-01",
 "info": [
  {
   "bbox": [
    0.0,
    0.0,
    0.0,
    0.0
   ],
   "pts": {
    "0": {
     "x": 129,
     "y": 45
    },
    "1": {
     "x": 97,
     "y": 71
    },
    "2": {
     "x": 83,
     "y": 52
    },
    "3": {
     "x": 59,
     "y": 57
    },
    "4": {
     "x": 54,
     "y": 57
    },
    "5": {
     "x": 73,
     "y": 36
    },
    "6": {
     "x": 52,
     "y": 29
    },
    "7": {
     "x": 36,
     "y": 36
    },
    "8": {
     "x": 19,
     "y": 43
    },
    "9": {
     "x": 78,
     "y": 36
    },
    "10": {
     "x": 54,
     "y": 43
    },
    "11": {
     "x": 36,
     "y": 55
    },
    "12": {
     "x": 17,
     "y": 67
    },
    "13": {
     "x": 90,
     "y": 43
    },
    "14": {
     "x": 66,
     "y": 52
    },
    "15": {
     "x": 45,
     "y": 71
    },
    "16": {
     "x": 33,
     "y": 88
    },
    "17": {
     "x": 99,
     "y": 52
    },
    "18": {
     "x": 80,
     "y": 60
    },
    "19": {
     "x": 66,
     "y": 67
    },
    "20": {
     "x": 50,
     "y": 78
    }
   }
  }
 ]
}