{
 "maker": "Eric.Lee",
 "date": "2021-02-01",
 "info": [
  {
   "bbox": [
    0.0,
    0.0,
    0.0,
    0.0
   ],
   "pts": {
    "0": {
     "x": 41,
     "y": 21
    },
    "1": {
     "x": 31,
     "y": 24
    },
    "2": {
     "x": 23,
     "y": 27
    },
    "3": {
     "x": 12,
     "y": 45
    },
    "4": {
     "x": 6,
     "y": 51
    },
    "5": {
     "x": 16,
     "y": 31
    },
    "6": {
     "x": 11,
     "y": 45
    },
    "7": {
     "x": 11,
     "y": 55
    },
    "8": {
     "x": 12,
     "y": 62
    },
    "9": {
     "x": 23,
     "y": 34
    },
    "10": {
     "x": 17,
     "y": 48
    },
    "11": {
     "x": 20,
     "y": 57
    },
    "12": {
     "x": 23,
     "y": 53
    },
    "13": {
     "x": 30,
     "y": 38
    },
    "14": {
     "x": 25,
     "y": 50
    },
    "15": {
     "x": 28,
     "y": 57
    },
    "16": {
     "x": 30,
     "y": 53
    },
    "17": {
     "x": 39,
     "y": 41
    },
    "18": {
     "x": 34,
     "y": 49
    },
    "19": {
     "x": 34,
     "y": 55
    },
    "20": {
     "x": 34,
     "y": 52
    }
   }
  }
 ]
}