{
 "maker": "Eric.Lee",
 "date": "2021-02-01",
 "info": [
  {
   "bbox": [
    0.0,
    0.0,
    0.0,
    0.0
   ],
   "pts": {
    "0": {
     "x": 22,
     "y": 22
    },
    "1": {
     "x": 9,
     "y": 32
    },
    "2": {
     "x": 8,
     "y": 47
    },
    "3": {
     "x": 6,
     "y": 58
    },
    "4": {
     "x": 6,
     "y": 71
    },
    "5": {
     "x": 24,
     "y": 60
    },
    "6": {
     "x": 21,
     "y": 73
    },
    "7": {
     "x": 13,
     "y": 79
    },
    "8": {
     "x": 5,
     "y": 82
    },
    "9": {
     "x": 31,
     "y": 61
    },
    "10": {
     "x": 26,
     "y": 78
    },
    "11": {
     "x": 16,
     "y": 82
    },
    "12": {
     "x": 6,
     "y": 84
    },
    "13": {
     "x": 29,
     "y": 61
    },
    "14": {
     "x": 27,
     "y": 76
    },
    "15": {
     "x": 18,
     "y": 82
    },
    "16": {
     "x": 8,
     "y": 82
    },
    "17": {
     "x": 29,
     "y": 61
    },
    "18": {
     "x": 26,
     "y": 73
    },
    "19": {
     "x": 19,
     "y": 79
    },
    "20": {
     "x": 13,
     "y": 81
    }
   }
  }
 ]
}