{
 "maker": "Eric.Lee",
 "date": "2021-02-01",
 "info": [
  {
   "bbox": [
    0.0,
    0.0,
    0.0,
    0.0
   ],
   "pts": {
    "0": {
     "x": 203,
     "y": 417
    },
    "1": {
     "x": 275,
     "y": 338
    },
    "2": {
     "x": 288,
     "y": 266
    },
    "3": {
     "x": 301,
     "y": 200
    },
    "4": {
     "x": 268,
     "y": 194
    },
    "5": {
     "x": 150,
     "y": 187
    },
    "6": {
     "x": 190,
     "y": 148
    },
    "7": {
     "x": 236,
     "y": 194
    },
    "8": {
     "x": 255,
     "y": 240
    },
    "9": {
     "x": 104,
     "y": 220
    },
    "10": {
     "x": 170,
     "y": 194
    },
    "11": {
     "x": 236,
     "y": 253
    },
    "12": {
     "x": 249,
     "y": 299
    },
    "13": {
     "x": 78,
     "y": 253
    },
    "14": {
     "x": 150,
     "y": 233
    },
    "15": {
     "x": 209,
     "y": 286
    },
    "16": {
     "x": 222,
     "y": 331
    },
    "17": {
     "x": 58,
     "y": 286
    },
    "18": {
     "x": 111,
     "y": 272
    },
    "19": {
     "x": 163,
     "y": 299
    },
    "20": {
     "x": 196,
     "y": 331
    }
   }
  }
 ]
}