{
 "maker": "Eric.Lee",
 "date": "2021-02-01",
 "info": [
  {
   "bbox": [
    0.0,
    0.0,
    0.0,
    0.0
   ],
   "pts": {
    "0": {
     "x": 18,
     "y": 100
    },
    "1": {
     "x": 9,
     "y": 83
    },
    "2": {
     "x": 9,
     "y": 69
    },
    "3": {
     "x": 9,
     "y": 59
    },
    "4": {
     "x": 17,
     "y": 50
    },
    "5": {
     "x": 2,
     "y": 58
    },
    "6": {
     "x": 9,
     "y": 45
    },
    "7": {
     "x": 18,
     "y": 41
    },
    "8": {
     "x": 31,
     "y": 41
    },
    "9": {
     "x": 7,
     "y": 54
    },
    "10": {
     "x": 17,
     "y": 32
    },
    "11": {
     "x": 28,
     "y": 34
    },
    "12": {
     "x": 41,
     "y": 41
    },
    "13": {
     "x": 15,
     "y": 52
    },
    "14": {
     "x": 20,
     "y": 32
    },
    "15": {
     "x": 35,
     "y": 32
    },
    "16": {
     "x": 44,
     "y": 43
    },
    "17": {
     "x": 28,
     "y": 52
    },
    "18": {
     "x": 35,
     "y": 39
    },
    "19": {
     "x": 46,
     "y": 43
    },
    "20": {
     "x": 52,
     "y": 54
    }
   }
  }
 ]
}