{
 "maker": "Eric.Lee",
 "date": "2021-02-01",
 "info": [
  {
   "bbox": [
    0.0,
    0.0,
    0.0,
    0.0
   ],
   "pts": {
    "0": {
     "x": 65,
     "y": 12
    },
    "1": {
     "x": 32,
     "y": 6
    },
    "2": {
     "x": 24,
     "y": 22
    },
    "3": {
     "x": 22,
     "y": 43
    },
    "4": {
     "x": 22,
     "y": 57
    },
    "5": {
     "x": 57,
     "y": 45
    },
    "6": {
     "x": 46,
     "y": 60
    },
    "7": {
     "x": 38,
     "y": 70
    },
    "8": {
     "x": 30,
     "y": 82
    },
    "9": {
     "x": 65,
     "y": 47
    },
    "10": {
     "x": 59,
     "y": 66
    },
    "11": {
     "x": 55,
     "y": 78
    },
    "12": {
     "x": 50,
     "y": 93
    },
    "13": {
     "x": 73,
     "y": 41
    },
    "14": {
     "x": 75,
     "y": 55
    },
    "15": {
     "x": 75,
     "y": 70
    },
    "16": {
     "x": 71,
     "y": 84
    },
    "17": {
     "x": 79,
     "y": 29
    },
    "18": {
     "x": 83,
     "y": 35
    },
    "19": {
     "x": 86,
     "y": 45
    },
    "20": {
     "x": 83,
     "y": 53
    }
   }
  }
 ]
}