{
 "maker": "Eric.Lee",
 "date": "2021-02-01",
 "info": [
  {
   "bbox": [
    0.0,
    0.0,
    0.0,
    0.0
   ],
   "pts": {
    "0": {
     "x": 289,
     "y": 183
    },
    "1": {
     "x": 266,
     "y": 227
    },
    "2": {
     "x": 244,
     "y": 255
    },
    "3": {
     "x": 216,
     "y": 277
    },
    "4": {
     "x": 194,
     "y": 299
    },
    "5": {
     "x": 200,
     "y": 216
    },
    "6": {
     "x": 155,
     "y": 221
    },
    "7": {
     "x": 122,
     "y": 227
    },
    "8": {
     "x": 94,
     "y": 227
    },
    "9": {
     "x": 194,
     "y": 188
    },
    "10": {
     "x": 144,
     "y": 183
    },
    "11": {
     "x": 111,
     "y": 177
    },
    "12": {
     "x": 83,
     "y": 171
    },
    "13": {
     "x": 194,
     "y": 166
    },
    "14": {
     "x": 150,
     "y": 155
    },
    "15": {
     "x": 122,
     "y": 149
    },
    "16": {
     "x": 88,
     "y": 138
    },
    "17": {
     "x": 205,
     "y": 149
    },
    "18": {
     "x": 172,
     "y": 138
    },
    "19": {
     "x": 150,
     "y": 127
    },
    "20": {
     "x": 127,
     "y": 110
    }
   }
  }
 ]
}