{
 "maker": "Eric.Lee",
 "date": "2021-02-01",
 "info": [
  {
   "bbox": [
    0.0,
    0.0,
    0.0,
    0.0
   ],
   "pts": {
    "0": {
     "x": 243,
     "y": 294
    },
    "1": {
     "x": 205,
     "y": 278
    },
    "2": {
     "x": 178,
     "y": 261
    },
    "3": {
     "x": 140,
     "y": 267
    },
    "4": {
     "x": 123,
     "y": 300
    },
    "5": {
     "x": 216,
     "y": 158
    },
    "6": {
     "x": 151,
     "y": 142
    },
    "7": {
     "x": 123,
     "y": 164
    },
    "8": {
     "x": 123,
     "y": 191
    },
    "9": {
     "x": 210,
     "y": 153
    },
    "10": {
     "x": 145,
     "y": 136
    },
    "11": {
     "x": 123,
     "y": 164
    },
    "12": {
     "x": 118,
     "y": 191
    },
    "13": {
     "x": 200,
     "y": 164
    },
    "14": {
     "x": 145,
     "y": 142
    },
    "15": {
     "x": 118,
     "y": 174
    },
    "16": {
     "x": 123,
     "y": 207
    },
    "17": {
     "x": 178,
     "y": 185
    },
    "18": {
     "x": 140,
     "y": 169
    },
    "19": {
     "x": 118,
     "y": 180
    },
    "20": {
     "x": 113,
     "y": 207
    }
   }
  }
 ]
}