{
 "maker": "Eric.Lee",
 "date": "2021-02-01",
 "info": [
  {
   "bbox": [
    0.0,
    0.0,
    0.0,
    0.0
   ],
   "pts": {
    "0": {
     "x": 229,
     "y": 412
    },
    "1": {
     "x": 199,
     "y": 412
    },
    "2": {
     "x": 176,
     "y": 360
    },
    "3": {
     "x": 146,
     "y": 300
    },
    "4": {
     "x": 102,
     "y": 248
    },
    "5": {
     "x": 191,
     "y": 263
    },
    "6": {
     "x": 146,
     "y": 210
    },
    "7": {
     "x": 109,
     "y": 173
    },
    "8": {
     "x": 64,
     "y": 128
    },
    "9": {
     "x": 161,
     "y": 263
    },
    "10": {
     "x": 154,
     "y": 203
    },
    "11": {
     "x": 109,
     "y": 173
    },
    "12": {
     "x": 64,
     "y": 136
    },
    "13": {
     "x": 109,
     "y": 255
    },
    "14": {
     "x": 94,
     "y": 225
    },
    "15": {
     "x": 79,
     "y": 203
    },
    "16": {
     "x": 49,
     "y": 173
    },
    "17": {
     "x": 87,
     "y": 277
    },
    "18": {
     "x": 79,
     "y": 270
    },
    "19": {
     "x": 72,
     "y": 255
    },
    "20": {
     "x": 57,
     "y": 233
    }
   }
  }
 ]
}