{
 "maker": "Eric.Lee",
 "date": "2021-02-01",
 "info": [
  {
   "bbox": [
    0.0,
    0.0,
    0.0,
    0.0
   ],
   "pts": {
    "0": {
     "x": 96,
     "y": 50
    },
    "1": {
     "x": 70,
     "y": 43
    },
    "2": {
     "x": 53,
     "y": 42
    },
    "3": {
     "x": 35,
     "y": 48
    },
    "4": {
     "x": 21,
     "y": 51
    },
    "5": {
     "x": 40,
     "y": 45
    },
    "6": {
     "x": 23,
     "y": 58
    },
    "7": {
     "x": 19,
     "y": 70
    },
    "8": {
     "x": 19,
     "y": 80
    },
    "9": {
     "x": 45,
     "y": 53
    },
    "10": {
     "x": 29,
     "y": 70
    },
    "11": {
     "x": 35,
     "y": 80
    },
    "12": {
     "x": 43,
     "y": 78
    },
    "13": {
     "x": 53,
     "y": 61
    },
    "14": {
     "x": 39,
     "y": 77
    },
    "15": {
     "x": 45,
     "y": 83
    },
    "16": {
     "x": 51,
     "y": 83
    },
    "17": {
     "x": 61,
     "y": 70
    },
    "18": {
     "x": 50,
     "y": 80
    },
    "19": {
     "x": 51,
     "y": 85
    },
    "20": {
     "x": 55,
     "y": 86
    }
   }
  }
 ]
}