{
 "maker": "Eric.Lee",
 "date": "2021-02-01",
 "info": [
  {
   "bbox": [
    0.0,
    0.0,
    0.0,
    0.0
   ],
   "pts": {
    "0": {
     "x": 76,
     "y": 167
    },
    "1": {
     "x": 113,
     "y": 167
    },
    "2": {
     "x": 142,
     "y": 160
    },
    "3": {
     "x": 172,
     "y": 145
    },
    "4": {
     "x": 201,
     "y": 112
    },
    "5": {
     "x": 124,
     "y": 145
    },
    "6": {
     "x": 139,
     "y": 127
    },
    "7": {
     "x": 146,
     "y": 116
    },
    "8": {
     "x": 161,
     "y": 93
    },
    "9": {
     "x": 98,
     "y": 145
    },
    "10": {
     "x": 102,
     "y": 123
    },
    "11": {
     "x": 106,
     "y": 104
    },
    "12": {
     "x": 102,
     "y": 60
    },
    "13": {
     "x": 76,
     "y": 156
    },
    "14": {
     "x": 65,
     "y": 138
    },
    "15": {
     "x": 61,
     "y": 116
    },
    "16": {
     "x": 54,
     "y": 75
    },
    "17": {
     "x": 50,
     "y": 171
    },
    "18": {
     "x": 35,
     "y": 152
    },
    "19": {
     "x": 24,
     "y": 145
    },
    "20": {
     "x": 10,
     "y": 119
    }
   }
  }
 ]
}