{
 "maker": "Eric.Lee",
 "date": "2021-02-01",
 "info": [
  {
   "bbox": [
    0.0,
    0.0,
    0.0,
    0.0
   ],
   "pts": {
    "0": {
     "x": 53,
     "y": 50
    },
    "1": {
     "x": 91,
     "y": 62
    },
    "2": {
     "x": 107,
     "y": 83
    },
    "3": {
     "x": 124,
     "y": 104
    },
    "4": {
     "x": 137,
     "y": 116
    },
    "5": {
     "x": 99,
     "y": 129
    },
    "6": {
     "x": 103,
     "y": 154
    },
    "7": {
     "x": 107,
     "y": 175
    },
    "8": {
     "x": 112,
     "y": 191
    },
    "9": {
     "x": 78,
     "y": 133
    },
    "10": {
     "x": 83,
     "y": 162
    },
    "11": {
     "x": 83,
     "y": 183
    },
    "12": {
     "x": 83,
     "y": 204
    },
    "13": {
     "x": 62,
     "y": 129
    },
    "14": {
     "x": 62,
     "y": 158
    },
    "15": {
     "x": 58,
     "y": 179
    },
    "16": {
     "x": 58,
     "y": 195
    },
    "17": {
     "x": 45,
     "y": 121
    },
    "18": {
     "x": 41,
     "y": 137
    },
    "19": {
     "x": 37,
     "y": 154
    },
    "20": {
     "x": 37,
     "y": 166
    }
   }
  }
 ]
}