{
 "maker": "Eric.Lee",
 "date": "2021-02-01",
 "info": [
  {
   "bbox": [
    0.0,
    0.0,
    0.0,
    0.0
   ],
   "pts": {
    "0": {
     "x": 33,
     "y": 99
    },
    "1": {
     "x": 35,
     "y": 75
    },
    "2": {
     "x": 39,
     "y": 65
    },
    "3": {
     "x": 59,
     "y": 55
    },
    "4": {
     "x": 71,
     "y": 49
    },
    "5": {
     "x": 35,
     "y": 59
    },
    "6": {
     "x": 57,
     "y": 55
    },
    "7": {
     "x": 71,
     "y": 55
    },
    "8": {
     "x": 83,
     "y": 55
    },
    "9": {
     "x": 37,
     "y": 69
    },
    "10": {
     "x": 59,
     "y": 65
    },
    "11": {
     "x": 75,
     "y": 63
    },
    "12": {
     "x": 87,
     "y": 61
    },
    "13": {
     "x": 39,
     "y": 81
    },
    "14": {
     "x": 61,
     "y": 75
    },
    "15": {
     "x": 77,
     "y": 73
    },
    "16": {
     "x": 87,
     "y": 71
    },
    "17": {
     "x": 45,
     "y": 91
    },
    "18": {
     "x": 63,
     "y": 87
    },
    "19": {
     "x": 75,
     "y": 83
    },
    "20": {
     "x": 85,
     "y": 81
    }
   }
  }
 ]
}