{
 "maker": "Eric.Lee",
 "date": "2021-02-01",
 "info": [
  {
   "bbox": [
    0.0,
    0.0,
    0.0,
    0.0
   ],
   "pts": {
    "0": {
     "x": 10,
     "y": 156
    },
    "1": {
     "x": 43,
     "y": 123
    },
    "2": {
     "x": 68,
     "y": 111
    },
    "3": {
     "x": 93,
     "y": 99
    },
    "4": {
     "x": 93,
     "y": 70
    },
    "5": {
     "x": 93,
     "y": 123
    },
    "6": {
     "x": 134,
     "y": 111
    },
    "7": {
     "x": 163,
     "y": 107
    },
    "8": {
     "x": 188,
     "y": 107
    },
    "9": {
     "x": 93,
     "y": 140
    },
    "10": {
     "x": 142,
     "y": 136
    },
    "11": {
     "x": 175,
     "y": 140
    },
    "12": {
     "x": 204,
     "y": 136
    },
    "13": {
     "x": 93,
     "y": 156
    },
    "14": {
     "x": 130,
     "y": 161
    },
    "15": {
     "x": 163,
     "y": 161
    },
    "16": {
     "x": 192,
     "y": 161
    },
    "17": {
     "x": 80,
     "y": 185
    },
    "18": {
     "x": 105,
     "y": 189
    },
    "19": {
     "x": 130,
     "y": 198
    },
    "20": {
     "x": 155,
     "y": 202
    }
   }
  }
 ]
}