{
 "maker": "Eric.Lee",
 "date": "2021-02-01",
 "info": [
  {
   "bbox": [
    0.0,
    0.0,
    0.0,
    0.0
   ],
   "pts": {
    "0": {
     "x": 119,
     "y": 148
    },
    "1": {
     "x": 159,
     "y": 136
    },
    "2": {
     "x": 199,
     "y": 116
    },
    "3": {
     "x": 227,
     "y": 108
    },
    "4": {
     "x": 239,
     "y": 87
    },
    "5": {
     "x": 171,
     "y": 71
    },
    "6": {
     "x": 191,
     "y": 55
    },
    "7": {
     "x": 211,
     "y": 43
    },
    "8": {
     "x": 235,
     "y": 35
    },
    "9": {
     "x": 135,
     "y": 43
    },
    "10": {
     "x": 155,
     "y": 59
    },
    "11": {
     "x": 179,
     "y": 112
    },
    "12": {
     "x": 195,
     "y": 148
    },
    "13": {
     "x": 102,
     "y": 55
    },
    "14": {
     "x": 114,
     "y": 63
    },
    "15": {
     "x": 127,
     "y": 87
    },
    "16": {
     "x": 143,
     "y": 99
    },
    "17": {
     "x": 78,
     "y": 95
    },
    "18": {
     "x": 62,
     "y": 87
    },
    "19": {
     "x": 50,
     "y": 79
    },
    "20": {
     "x": 26,
     "y": 59
    }
   }
  }
 ]
}