{
 "maker": "Eric.Lee",
 "date": "2021-02-01",
 "info": [
  {
   "bbox": [
    0.0,
    0.0,
    0.0,
    0.0
   ],
   "pts": {
    "0": {
     "x": 248,
     "y": 78
    },
    "1": {
     "x": 225,
     "y": 128
    },
    "2": {
     "x": 189,
     "y": 150
    },
    "3": {
     "x": 157,
     "y": 159
    },
    "4": {
     "x": 125,
     "y": 155
    },
    "5": {
     "x": 162,
     "y": 96
    },
    "6": {
     "x": 125,
     "y": 105
    },
    "7": {
     "x": 98,
     "y": 128
    },
    "8": {
     "x": 84,
     "y": 141
    },
    "9": {
     "x": 152,
     "y": 78
    },
    "10": {
     "x": 116,
     "y": 82
    },
    "11": {
     "x": 80,
     "y": 96
    },
    "12": {
     "x": 48,
     "y": 105
    },
    "13": {
     "x": 148,
     "y": 64
    },
    "14": {
     "x": 116,
     "y": 73
    },
    "15": {
     "x": 84,
     "y": 82
    },
    "16": {
     "x": 57,
     "y": 87
    },
    "17": {
     "x": 152,
     "y": 60
    },
    "18": {
     "x": 130,
     "y": 69
    },
    "19": {
     "x": 112,
     "y": 73
    },
    "20": {
     "x": 89,
     "y": 82
    }
   }
  }
 ]
}