{
 "maker": "Eric.Lee",
 "date": "2021-02-01",
 "info": [
  {
   "bbox": [
    0.0,
    0.0,
    0.0,
    0.0
   ],
   "pts": {
    "0": {
     "x": 98,
     "y": 186
    },
    "1": {
     "x": 109,
     "y": 146
    },
    "2": {
     "x": 135,
     "y": 120
    },
    "3": {
     "x": 154,
     "y": 102
    },
    "4": {
     "x": 150,
     "y": 76
    },
    "5": {
     "x": 179,
     "y": 131
    },
    "6": {
     "x": 220,
     "y": 127
    },
    "7": {
     "x": 253,
     "y": 127
    },
    "8": {
     "x": 283,
     "y": 131
    },
    "9": {
     "x": 187,
     "y": 161
    },
    "10": {
     "x": 213,
     "y": 172
    },
    "11": {
     "x": 202,
     "y": 179
    },
    "12": {
     "x": 176,
     "y": 175
    },
    "13": {
     "x": 187,
     "y": 186
    },
    "14": {
     "x": 220,
     "y": 190
    },
    "15": {
     "x": 235,
     "y": 197
    },
    "16": {
     "x": 253,
     "y": 201
    },
    "17": {
     "x": 179,
     "y": 212
    },
    "18": {
     "x": 198,
     "y": 220
    },
    "19": {
     "x": 216,
     "y": 227
    },
    "20": {
     "x": 238,
     "y": 231
    }
   }
  }
 ]
}