{
 "maker": "Eric.Lee",
 "date": "2021-02-01",
 "info": [
  {
   "bbox": [
    0.0,
    0.0,
    0.0,
    0.0
   ],
   "pts": {
    "0": {
     "x": 198,
     "y": 75
    },
    "1": {
     "x": 202,
     "y": 126
    },
    "2": {
     "x": 177,
     "y": 155
    },
    "3": {
     "x": 147,
     "y": 163
    },
    "4": {
     "x": 110,
     "y": 168
    },
    "5": {
     "x": 114,
     "y": 122
    },
    "6": {
     "x": 72,
     "y": 134
    },
    "7": {
     "x": 59,
     "y": 155
    },
    "8": {
     "x": 51,
     "y": 168
    },
    "9": {
     "x": 101,
     "y": 96
    },
    "10": {
     "x": 59,
     "y": 105
    },
    "11": {
     "x": 43,
     "y": 130
    },
    "12": {
     "x": 43,
     "y": 147
    },
    "13": {
     "x": 101,
     "y": 80
    },
    "14": {
     "x": 64,
     "y": 84
    },
    "15": {
     "x": 51,
     "y": 105
    },
    "16": {
     "x": 51,
     "y": 122
    },
    "17": {
     "x": 105,
     "y": 71
    },
    "18": {
     "x": 84,
     "y": 71
    },
    "19": {
     "x": 68,
     "y": 80
    },
    "20": {
     "x": 59,
     "y": 96
    }
   }
  }
 ]
}