{
 "maker": "Eric.Lee",
 "date": "2021-02-01",
 "info": [
  {
   "bbox": [
    0.0,
    0.0,
    0.0,
    0.0
   ],
   "pts": {
    "0": {
     "x": 10,
     "y": 24
    },
    "1": {
     "x": 31,
     "y": 48
    },
    "2": {
     "x": 34,
     "y": 69
    },
    "3": {
     "x": 33,
     "y": 83
    },
    "4": {
     "x": 31,
     "y": 98
    },
    "5": {
     "x": 16,
     "y": 81
    },
    "6": {
     "x": 20,
     "y": 102
    },
    "7": {
     "x": 27,
     "y": 102
    },
    "8": {
     "x": 34,
     "y": 94
    },
    "9": {
     "x": 7,
     "y": 83
    },
    "10": {
     "x": 16,
     "y": 102
    },
    "11": {
     "x": 27,
     "y": 102
    },
    "12": {
     "x": 31,
     "y": 94
    },
    "13": {
     "x": 7,
     "y": 83
    },
    "14": {
     "x": 14,
     "y": 100
    },
    "15": {
     "x": 27,
     "y": 98
    },
    "16": {
     "x": 31,
     "y": 93
    },
    "17": {
     "x": 7,
     "y": 81
    },
    "18": {
     "x": 12,
     "y": 91
    },
    "19": {
     "x": 18,
     "y": 96
    },
    "20": {
     "x": 23,
     "y": 87
    }
   }
  }
 ]
}