{
 "maker": "Eric.Lee",
 "date": "2021-02-01",
 "info": [
  {
   "bbox": [
    0.0,
    0.0,
    0.0,
    0.0
   ],
   "pts": {
    "0": {
     "x": 218,
     "y": 120
    },
    "1": {
     "x": 186,
     "y": 160
    },
    "2": {
     "x": 154,
     "y": 160
    },
    "3": {
     "x": 126,
     "y": 156
    },
    "4": {
     "x": 98,
     "y": 160
    },
    "5": {
     "x": 146,
     "y": 116
    },
    "6": {
     "x": 122,
     "y": 116
    },
    "7": {
     "x": 98,
     "y": 108
    },
    "8": {
     "x": 70,
     "y": 112
    },
    "9": {
     "x": 142,
     "y": 96
    },
    "10": {
     "x": 118,
     "y": 80
    },
    "11": {
     "x": 90,
     "y": 64
    },
    "12": {
     "x": 66,
     "y": 48
    },
    "13": {
     "x": 138,
     "y": 116
    },
    "14": {
     "x": 118,
     "y": 116
    },
    "15": {
     "x": 90,
     "y": 116
    },
    "16": {
     "x": 66,
     "y": 116
    },
    "17": {
     "x": 142,
     "y": 148
    },
    "18": {
     "x": 122,
     "y": 148
    },
    "19": {
     "x": 106,
     "y": 148
    },
    "20": {
     "x": 94,
     "y": 156
    }
   }
  }
 ]
}