{
 "maker": "Eric.Lee",
 "date": "2021-02-01",
 "info": [
  {
   "bbox": [
    0.0,
    0.0,
    0.0,
    0.0
   ],
   "pts": {
    "0": {
     "x": 56,
     "y": 56
    },
    "1": {
     "x": 100,
     "y": 60
    },
    "2": {
     "x": 127,
     "y": 74
    },
    "3": {
     "x": 140,
     "y": 100
    },
    "4": {
     "x": 162,
     "y": 118
    },
    "5": {
     "x": 100,
     "y": 109
    },
    "6": {
     "x": 113,
     "y": 131
    },
    "7": {
     "x": 122,
     "y": 149
    },
    "8": {
     "x": 131,
     "y": 166
    },
    "9": {
     "x": 83,
     "y": 122
    },
    "10": {
     "x": 96,
     "y": 153
    },
    "11": {
     "x": 105,
     "y": 179
    },
    "12": {
     "x": 118,
     "y": 206
    },
    "13": {
     "x": 60,
     "y": 131
    },
    "14": {
     "x": 69,
     "y": 162
    },
    "15": {
     "x": 83,
     "y": 184
    },
    "16": {
     "x": 96,
     "y": 201
    },
    "17": {
     "x": 43,
     "y": 131
    },
    "18": {
     "x": 38,
     "y": 153
    },
    "19": {
     "x": 34,
     "y": 171
    },
    "20": {
     "x": 30,
     "y": 193
    }
   }
  }
 ]
}