{
 "maker": "Eric.Lee",
 "date": "2021-02-01",
 "info": [
  {
   "bbox": [
    0.0,
    0.0,
    0.0,
    0.0
   ],
   "pts": {
    "0": {
     "x": 212,
     "y": 76
    },
    "1": {
     "x": 216,
     "y": 122
    },
    "2": {
     "x": 201,
     "y": 141
    },
    "3": {
     "x": 182,
     "y": 152
    },
    "4": {
     "x": 171,
     "y": 171
    },
    "5": {
     "x": 163,
     "y": 92
    },
    "6": {
     "x": 129,
     "y": 103
    },
    "7": {
     "x": 95,
     "y": 118
    },
    "8": {
     "x": 69,
     "y": 122
    },
    "9": {
     "x": 148,
     "y": 76
    },
    "10": {
     "x": 114,
     "y": 99
    },
    "11": {
     "x": 87,
     "y": 122
    },
    "12": {
     "x": 57,
     "y": 122
    },
    "13": {
     "x": 140,
     "y": 65
    },
    "14": {
     "x": 106,
     "y": 80
    },
    "15": {
     "x": 80,
     "y": 99
    },
    "16": {
     "x": 53,
     "y": 118
    },
    "17": {
     "x": 137,
     "y": 61
    },
    "18": {
     "x": 106,
     "y": 65
    },
    "19": {
     "x": 87,
     "y": 61
    },
    "20": {
     "x": 65,
     "y": 54
    }
   }
  }
 ]
}