{
 "maker": "Eric.Lee",
 "date": "2021-02-01",
 "info": [
  {
   "bbox": [
    0.0,
    0.0,
    0.0,
    0.0
   ],
   "pts": {
    "0": {
     "x": 23,
     "y": 71
    },
    "1": {
     "x": 42,
     "y": 58
    },
    "2": {
     "x": 41,
     "y": 50
    },
    "3": {
     "x": 39,
     "y": 40
    },
    "4": {
     "x": 42,
     "y": 35
    },
    "5": {
     "x": 21,
     "y": 41
    },
    "6": {
     "x": 26,
     "y": 30
    },
    "7": {
     "x": 36,
     "y": 28
    },
    "8": {
     "x": 45,
     "y": 30
    },
    "9": {
     "x": 24,
     "y": 45
    },
    "10": {
     "x": 35,
     "y": 37
    },
    "11": {
     "x": 44,
     "y": 39
    },
    "12": {
     "x": 51,
     "y": 45
    },
    "13": {
     "x": 26,
     "y": 50
    },
    "14": {
     "x": 35,
     "y": 44
    },
    "15": {
     "x": 42,
     "y": 45
    },
    "16": {
     "x": 47,
     "y": 49
    },
    "17": {
     "x": 28,
     "y": 54
    },
    "18": {
     "x": 32,
     "y": 52
    },
    "19": {
     "x": 39,
     "y": 51
    },
    "20": {
     "x": 41,
     "y": 51
    }
   }
  }
 ]
}