{
 "maker": "Eric.Lee",
 "date": "2021-02-01",
 "info": [
  {
   "bbox": [
    0.0,
    0.0,
    0.0,
    0.0
   ],
   "pts": {
    "0": {
     "x": 51,
     "y": 200
    },
    "1": {
     "x": 82,
     "y": 180
    },
    "2": {
     "x": 105,
     "y": 150
    },
    "3": {
     "x": 105,
     "y": 116
    },
    "4": {
     "x": 98,
     "y": 100
    },
    "5": {
     "x": 118,
     "y": 130
    },
    "6": {
     "x": 135,
     "y": 100
    },
    "7": {
     "x": 128,
     "y": 76
    },
    "8": {
     "x": 112,
     "y": 76
    },
    "9": {
     "x": 92,
     "y": 120
    },
    "10": {
     "x": 102,
     "y": 80
    },
    "11": {
     "x": 95,
     "y": 86
    },
    "12": {
     "x": 92,
     "y": 103
    },
    "13": {
     "x": 68,
     "y": 116
    },
    "14": {
     "x": 78,
     "y": 80
    },
    "15": {
     "x": 71,
     "y": 96
    },
    "16": {
     "x": 71,
     "y": 110
    },
    "17": {
     "x": 38,
     "y": 116
    },
    "18": {
     "x": 55,
     "y": 80
    },
    "19": {
     "x": 55,
     "y": 100
    },
    "20": {
     "x": 48,
     "y": 110
    }
   }
  }
 ]
}